ossv_scanner/__init__.py
ossv_scanner/main.py
ossv_scanner/caching/__init__.py
ossv_scanner/caching/cache.py
ossv_scanner/parsers/__init__.py
ossv_scanner/parsers/dependency.py
ossv_scanner/parsers/java_parser.py
ossv_scanner/parsers/javascript_parser.py
ossv_scanner/parsers/parser_base.py
ossv_scanner/parsers/python_parser.py
ossv_scanner/reporting/__init__.py
ossv_scanner/reporting/reporter.py
ossv_scanner/reporting/templates/__init__.py
ossv_scanner/sbom/__init__.py
ossv_scanner/sbom/generator.py
ossv_scanner/utils/__init__.py
ossv_scanner/utils/chaoss_metrics.py
ossv_scanner/utils/metrics.py
ossv_scanner/visualization/__init__.py
ossv_scanner/visualization/visualizer.py
ossv_scanner/vulnerability/__init__.py
ossv_scanner/vulnerability/nvd_client.py
ossv_scanner/vulnerability/vulnerability.py
tests/__init__.py
tests/test_caching.py
tests/test_chaoss_metrics.py
tests/test_parsers.py
tests/test_sbom.py
tests/test_vulnerability.py
ossv_scanner-0.1.0.dist-info/METADATA
ossv_scanner-0.1.0.dist-info/WHEEL
ossv_scanner-0.1.0.dist-info/entry_points.txt
ossv_scanner-0.1.0.dist-info/top_level.txt
ossv_scanner-0.1.0.dist-info/RECORD
