Metadata-Version: 2.4
Name: ossv-scanner
Version: 0.1.0
Summary: A tool for scanning OSS projects for dependencies and vulnerabilities
Home-page: https://github.com/maxg67/OSS.git
Author: Your Name
Author-email: your.email@example.com
Classifier: Programming Language :: Python :: 3
Classifier: License :: OSI Approved :: MIT License
Classifier: Operating System :: OS Independent
Requires-Python: >=3.8
Requires-Dist: requests>=2.28.0
Requires-Dist: cyclonedx-bom>=3.0.0
Requires-Dist: matplotlib>=3.6.0
Requires-Dist: seaborn>=0.12.0
Requires-Dist: plotly>=5.10.0
Requires-Dist: pandas>=1.5.0
Requires-Dist: aiohttp>=3.8.0
Requires-Dist: asyncio>=3.4.3
Requires-Dist: diskcache>=5.4.0
Requires-Dist: jinja2>=3.1.0
Requires-Dist: tqdm>=4.64.0
Requires-Dist: lxml>=4.9.0
Requires-Dist: beautifulsoup4>=4.11.0
Requires-Dist: packaging>=21.3
Requires-Dist: python-dateutil>=2.8.2
Requires-Dist: colorama>=0.4.5
Requires-Dist: click>=8.1.0
Requires-Dist: rich>=12.5.0
Dynamic: author
Dynamic: author-email
Dynamic: classifier
Dynamic: description
Dynamic: description-content-type
Dynamic: home-page
Dynamic: requires-dist
Dynamic: requires-python
Dynamic: summary
